AUTHORS.rst
CONTRIBUTING.rst
HISTORY.rst
LICENSE
MANIFEST.in
README.rst
setup.cfg
setup.py
docs/Makefile
docs/make.bat
docs/source/authors.rst
docs/source/conf.py
docs/source/contributing.rst
docs/source/history.rst
docs/source/index.rst
docs/source/installation.rst
docs/source/readme.rst
docs/source/usage.rst
docs/source/_static/img/favicon.png
docs/source/_static/img/nuclei.png
nuclei/__init__.py
nuclei/nuclei.py
nuclei.egg-info/PKG-INFO
nuclei.egg-info/SOURCES.txt
nuclei.egg-info/dependency_links.txt
nuclei.egg-info/not-zip-safe
nuclei.egg-info/top_level.txt
tests/__init__.py
tests/test_nuclei.py