Metadata-Version: 1.1
Name: nuclei
Version: 0.1.0
Summary: 2018 Kaggle Data Science Bowl
Home-page: https://github.com/yngtodd/nuclei
Author: Todd Young
Author-email: young.todd.mk@gmail.com
License: MIT license
Keywords: nuclei
Platform: UNKNOWN
Classifier: Development Status :: 2 - Pre-Alpha
Classifier: Intended Audience :: Developers
Classifier: License :: OSI Approved :: MIT License
Classifier: Natural Language :: English
Classifier: Programming Language :: Python :: 3
Classifier: Programming Language :: Python :: 3.3
Classifier: Programming Language :: Python :: 3.4
Classifier: Programming Language :: Python :: 3.5
Classifier: Programming Language :: Python :: 3.6
